pytvpaint/__init__.py
pytvpaint/camera.py
pytvpaint/clip.py
pytvpaint/george/__init__.py
pytvpaint/george/client/__init__.py
pytvpaint/george/client/parse.py
pytvpaint/george/client/rpc.py
pytvpaint/george/exceptions.py
pytvpaint/george/grg_base.py
pytvpaint/george/grg_camera.py
pytvpaint/george/grg_clip.py
pytvpaint/george/grg_layer.py
pytvpaint/george/grg_project.py
pytvpaint/george/grg_scene.py
pytvpaint/layer.py
pytvpaint/project.py
pytvpaint/py.typed
pytvpaint/scene.py
pytvpaint/sound.py
pytvpaint/utils.py
pytvpaint-1.0.2.dist-info/LICENSE.md
pytvpaint-1.0.2.dist-info/METADATA
pytvpaint-1.0.2.dist-info/WHEEL
pytvpaint-1.0.2.dist-info/RECORD
