Metadata-Version: 2.1
Name: pytvpaint
Version: 1.0.2
Summary: Python scripting for TVPaint
Home-page: https://github.com/brunchstudio/pytvpaint
License: MIT
Keywords: tvpaint,brunch,tvp,george
Author: Brunch Studio Developers
Author-email: dev@brunchstudio.tv
Requires-Python: >=3.9
Classifier: License :: OSI Approved :: MIT License
Classifier: Programming Language :: Python :: 3
Classifier: Programming Language :: Python :: 3.9
Classifier: Programming Language :: Python :: 3.10
Classifier: Programming Language :: Python :: 3.11
Classifier: Programming Language :: Python :: 3.12
Requires-Dist: fileseq (>=2.0.0,<3.0.0)
Requires-Dist: typing-extensions (>=4.9.0,<5.0.0)
Requires-Dist: websocket-client (>=1.7.0,<2.0.0)
Project-URL: Documentation, https://brunchstudio.github.io/pytvpaint/
Project-URL: Repository, https://github.com/brunchstudio/pytvpaint
